mycalc/calculator.py
josubin-0.0.1.dist-info/METADATA
josubin-0.0.1.dist-info/WHEEL
josubin-0.0.1.dist-info/top_level.txt
josubin-0.0.1.dist-info/RECORD
