Metadata-Version: 2.1
Name: josubin
Version: 0.0.1
Summary: my calculator
Home-page: https://github.com/josubin/mycalc
Download-URL: https://github.com/josubin/mycalc
Author: josubin
License: UNKNOWN
Platform: UNKNOWN
Classifier: Programming Language :: Python :: 3
